<?xml version="1.0" encoding="UTF-8"?>
<objects serializationModel="Studio.02.01.00">
	<object class="AudioFile" id="{c2389eb0-a318-4d5c-8f49-42ebb2be25fe}">
		<property name="assetPath">
			<value>Title_V1_R7.wav</value>
		</property>
		<property name="isStreaming">
			<value>true</value>
		</property>
		<property name="frequencyInKHz">
			<value>44.0999985</value>
		</property>
		<property name="channelCount">
			<value>2</value>
		</property>
		<property name="length">
			<value>222.76458049886622</value>
		</property>
		<relationship name="masterAssetFolder">
			<destination>{175afa41-df14-4da2-9f38-31df5c591e53}</destination>
		</relationship>
	</object>
</objects>
