<?xml version="1.0" encoding="UTF-8"?>
<objects serializationModel="Studio.02.01.00">
	<object class="AudioFile" id="{d7268cd7-ba86-42f7-ad92-3bc1b7f50b73}">
		<property name="assetPath">
			<value>NewConstellation_Test01 - 0018 - Instrument - C4.wav</value>
		</property>
		<property name="isStreaming">
			<value>true</value>
		</property>
		<property name="frequencyInKHz">
			<value>44.0999985</value>
		</property>
		<property name="channelCount">
			<value>2</value>
		</property>
		<property name="length">
			<value>14</value>
		</property>
		<relationship name="masterAssetFolder">
			<destination>{175afa41-df14-4da2-9f38-31df5c591e53}</destination>
		</relationship>
	</object>
</objects>
